README.md
setup.cfg
setup.py
mllpa/__init__.py
mllpa/input_output.py
mllpa/interface_communication.py
mllpa/model_generation.py
mllpa/neighbour_analysis.py
mllpa/read_simulation.py
mllpa/system_class.py
mllpa.egg-info/PKG-INFO
mllpa.egg-info/SOURCES.txt
mllpa.egg-info/dependency_links.txt
mllpa.egg-info/requires.txt
mllpa.egg-info/top_level.txt
mllpa/configurations/__init__.py
mllpa/configurations/coordinates.py
mllpa/configurations/distances.py