Metadata-Version: 2.1
Name: mllpa
Version: 1.0.1
Summary: Machine Learning-assisted Lipid Phase Analysis - Module to analyse a lipid membrane generated using Molecular Dynamics (MD) simulations and predict the thermodynamical phase of the lipids.
Home-page: https://vivien-walter.github.io/mllpa/
Author: Vivien WALTER
Author-email: walter.vivien@gmail.com
License: GPL3.0
Download-URL: https://github.com/vivien-walter/mllpa/archive/v_1a.tar.gz
Platform: UNKNOWN
